shownewlistedit.py
shownewlistedit-1.0.0.dist-info/METADATA
shownewlistedit-1.0.0.dist-info/WHEEL
shownewlistedit-1.0.0.dist-info/RECORD
